simple_service/__init__.py
simple_service/simple_service.py
ops_py_example_code-1.3.12.dist-info/LICENSE
ops_py_example_code-1.3.12.dist-info/METADATA
ops_py_example_code-1.3.12.dist-info/WHEEL
ops_py_example_code-1.3.12.dist-info/top_level.txt
ops_py_example_code-1.3.12.dist-info/RECORD
