Metadata-Version: 2.2
Name: ops-py-example-code
Version: 1.3.12
Summary: Code example
License: MIT License
License-File: LICENSE
Requires-Dist: certifi==2024.8.30
Requires-Dist: charset-normalizer==3.4.0
Requires-Dist: idna==3.10
Requires-Dist: pip==24.3.1
Requires-Dist: requests==2.32.3
Requires-Dist: setuptools==75.5.0
Requires-Dist: urllib3==2.2.3
Requires-Dist: wheel==0.45.0
